composeml/__init__.py
composeml/conftest.py
composeml/label_maker.py
composeml/label_search.py
composeml/update_checker.py
composeml/version.py
composeml/data_slice/__init__.py
composeml/data_slice/extension.py
composeml/data_slice/generator.py
composeml/data_slice/offset.py
composeml/demos/__init__.py
composeml/demos/transactions.csv
composeml/label_times/__init__.py
composeml/label_times/description.py
composeml/label_times/deserialize.py
composeml/label_times/object.py
composeml/label_times/plots.py
composeml/tests/__init__.py
composeml/tests/test_datasets.py
composeml/tests/test_featuretools.py
composeml/tests/test_label_maker.py
composeml/tests/test_label_plots.py
composeml/tests/test_label_serialization.py
composeml/tests/test_label_times.py
composeml/tests/test_version.py
composeml/tests/utils.py
composeml/tests/requirement_files/latest_core_dependencies.txt
composeml/tests/requirement_files/minimum_core_requirements.txt
composeml/tests/requirement_files/minimum_test_requirements.txt
composeml/tests/test_data_slice/__init__.py
composeml/tests/test_data_slice/test_extension.py
composeml/tests/test_data_slice/test_offset.py
composeml/tests/test_label_transforms/__init__.py
composeml/tests/test_label_transforms/test_bin.py
composeml/tests/test_label_transforms/test_lead.py
composeml/tests/test_label_transforms/test_sample.py
composeml/tests/test_label_transforms/test_threshold.py
composeml-0.10.1.dist-info/LICENSE
composeml-0.10.1.dist-info/METADATA
composeml-0.10.1.dist-info/WHEEL
composeml-0.10.1.dist-info/top_level.txt
composeml-0.10.1.dist-info/RECORD
