Metadata-Version: 2.1
Name: composeml
Version: 0.10.1
Summary: a framework for automated prediction engineering
Author-email: "Alteryx, Inc." <open_source_support@alteryx.com>
Maintainer-email: "Alteryx, Inc." <open_source_support@alteryx.com>
License: BSD 3-clause
Project-URL: Documentation, https://compose.alteryx.com
Project-URL: Source Code, https://github.com/alteryx/compose/
Project-URL: Changes, https://compose.alteryx.com/en/latest/release_notes.html
Project-URL: Issue Tracker, https://github.com/alteryx/compose/issues
Project-URL: Twitter, https://twitter.com/alteryxoss
Project-URL: Chat, https://join.slack.com/t/alteryx-oss/shared_invite/zt-182tyvuxv-NzIn6eiCEf8TBziuKp0bNA
Keywords: prediction engineering,data science,machine learning
Classifier: Development Status :: 5 - Production/Stable
Classifier: Intended Audience :: Science/Research
Classifier: Intended Audience :: Developers
Classifier: Topic :: Software Development
Classifier: Topic :: Scientific/Engineering
Classifier: Programming Language :: Python
Classifier: Programming Language :: Python :: 3
Classifier: Programming Language :: Python :: 3.8
Classifier: Programming Language :: Python :: 3.9
Classifier: Programming Language :: Python :: 3.10
Classifier: Programming Language :: Python :: 3.11
Classifier: Operating System :: OS Independent
Requires-Python: <4,>=3.8
License-File: LICENSE
Requires-Dist: pandas (>=1.3.0)
Requires-Dist: tqdm (>=4.32.0)
Requires-Dist: matplotlib (>=3.3.3)
Requires-Dist: seaborn (>=0.11.0)
Provides-Extra: complete
Requires-Dist: composeml[updater] ; extra == 'complete'
Provides-Extra: dev
Requires-Dist: codecov (==2.1.12) ; extra == 'dev'
Requires-Dist: flake8 (==4.0.1) ; extra == 'dev'
Requires-Dist: isort (==5.9.3) ; extra == 'dev'
Requires-Dist: black (==22.10.0) ; extra == 'dev'
Requires-Dist: nbsphinx (==0.8.7) ; extra == 'dev'
Requires-Dist: pydata-sphinx-theme (==0.7.1) ; extra == 'dev'
Requires-Dist: Sphinx (==4.2.0) ; extra == 'dev'
Requires-Dist: sphinx-inline-tabs (==2022.1.2b11) ; extra == 'dev'
Requires-Dist: sphinx-copybutton (==0.4.0) ; extra == 'dev'
Requires-Dist: myst-parser (==0.16.1) ; extra == 'dev'
Requires-Dist: nbconvert (==6.4.5) ; extra == 'dev'
Requires-Dist: ipython (==7.31.1) ; extra == 'dev'
Requires-Dist: pygments (==2.10.0) ; extra == 'dev'
Requires-Dist: jupyter (==1.0.0) ; extra == 'dev'
Requires-Dist: pandoc (==1.1.0) ; extra == 'dev'
Requires-Dist: ipykernel (==6.4.2) ; extra == 'dev'
Requires-Dist: scikit-learn (!=0.22,<1.2.0,>=0.20.0) ; extra == 'dev'
Provides-Extra: docs
Requires-Dist: evalml (>=0.45.0) ; extra == 'docs'
Provides-Extra: test
Requires-Dist: pip (>=21.3.1) ; extra == 'test'
Requires-Dist: pytest-cov (==3.0.0) ; extra == 'test'
Requires-Dist: pytest-xdist (>=2.5.0) ; extra == 'test'
Requires-Dist: wheel (>=0.33.1) ; extra == 'test'
Requires-Dist: featuretools (>=1.4.0) ; extra == 'test'
Requires-Dist: woodwork (>=0.11.0) ; extra == 'test'
Requires-Dist: pyarrow (>=3.0.0) ; extra == 'test'
Provides-Extra: updater
Requires-Dist: alteryx-open-src-update-checker (>=2.1.0) ; extra == 'updater'
